getprojects.py
setup.py
GetProjects.egg-info/PKG-INFO
GetProjects.egg-info/SOURCES.txt
GetProjects.egg-info/dependency_links.txt
GetProjects.egg-info/entry_points.txt
GetProjects.egg-info/pbr.json
GetProjects.egg-info/top_level.txt