Metadata-Version: 1.1
Name: GetProjects
Version: 0.1.0
Summary: Clone all your GitHub repos with one command.
Home-page: https://github.com/gkbrk/GetProjects
Author: Gokberk Yaltirakli
Author-email: webdosusb@gmail.com
License: UNKNOWN
Keywords: github,git,repo
Platform: UNKNOWN
Requires: requests
